classifier/__init__.py
classifier/sugeno_classifier.py
classifier/mediator/__init__.py
classifier/mediator/fitter.py
classifier/mediator/mediator.py
classifier/mediator/predictor.py
classifier/mediator/components/__init__.py
classifier/mediator/components/capacity.py
classifier/mediator/components/feature_transformation.py
classifier/mediator/components/helper.py
classifier/mediator/components/sugeno_integral.py
classifier/mediator/components/threshold.py
sugeno_classifier-1.0.1.dist-info/LICENSE
sugeno_classifier-1.0.1.dist-info/METADATA
sugeno_classifier-1.0.1.dist-info/WHEEL
sugeno_classifier-1.0.1.dist-info/top_level.txt
sugeno_classifier-1.0.1.dist-info/RECORD
