Metadata-Version: 2.1
Name: sugeno-classifier
Version: 1.0.1
Summary: Implementation of the Sugeno classifier
Home-page: https://github.com/smeyer198/sugeno-classifier
Author: Sven Meyer
License: MIT
Platform: UNKNOWN
Classifier: Programming Language :: Python :: 3.8
Requires-Dist: numpy (>=1.19.0)
Requires-Dist: scikit-learn (>=0.24.1)
Requires-Dist: pulp (>=2.4)
